docx_live_reload/main.py
docx_live_reload-0.0.6.dist-info/LICENSE
docx_live_reload-0.0.6.dist-info/METADATA
docx_live_reload-0.0.6.dist-info/WHEEL
docx_live_reload-0.0.6.dist-info/entry_points.txt
docx_live_reload-0.0.6.dist-info/top_level.txt
docx_live_reload-0.0.6.dist-info/RECORD
