Metadata-Version: 2.1
Name: docx-live-reload
Version: 0.0.6
Summary: Preview a Docx file in MS Word. Modify the Docx file or the extracted document.xml or style.xml and the document will reload in MS Word and show the changes.
Home-page: https://github.com/idtareq/docx-live-reload
Author: Tareq Ibrahim
Author-email: idtareq@gmail.com
License: MIT
Keywords: word,reload,docx,preview
Requires-Python: >=3.6.1
License-File: LICENSE
Requires-Dist: lxml
Requires-Dist: pywin32
Requires-Dist: importlib-metadata ; python_version < "3.8"
